MANIFEST.in
README.rst
setup.py
src/null.py
src/null.egg-info/PKG-INFO
src/null.egg-info/SOURCES.txt
src/null.egg-info/dependency_links.txt
src/null.egg-info/not-zip-safe
src/null.egg-info/requires.txt
src/null.egg-info/top_level.txt
test/test_null.py